judi/__init__.py
judi/file.py
judi/judi.py
judi/paramdb.py
judi/task.py
judi/utils.py
judi/version.py
judi-0.0.0.4.dist-info/LICENSE
judi-0.0.0.4.dist-info/METADATA
judi-0.0.0.4.dist-info/WHEEL
judi-0.0.0.4.dist-info/top_level.txt
judi-0.0.0.4.dist-info/RECORD
